_k2.cpython-310-darwin.so
k2/__init__.py
k2/autograd.py
k2/autograd_utils.py
k2/ctc_loss.py
k2/decode.py
k2/dense_fsa_vec.py
k2/fsa.py
k2/fsa_algo.py
k2/fsa_properties.py
k2/mutual_information.py
k2/mwer_loss.py
k2/nbest.py
k2/online_dense_intersecter.py
k2/ops.py
k2/rnnt_decode.py
k2/rnnt_loss.py
k2/symbol_table.py
k2/torch_version.py
k2/utils.py
k2/include/k2/torch_api.h
k2/lib/libk2_log.dylib
k2/lib/libk2_torch.dylib
k2/lib/libk2_torch_api.dylib
k2/lib/libk2context.dylib
k2/lib/libk2fsa.dylib
k2/ragged/__init__.py
k2/share/cmake/k2/k2Config.cmake
k2/share/cmake/k2/k2ConfigVersion.cmake
k2/sparse/__init__.py
k2/sparse/autograd.py
k2/version/__init__.py
k2/version/__main__.py
k2/version/version.py
k2-1.24.1.dist-info/LICENSE
k2-1.24.1.dist-info/METADATA
k2-1.24.1.dist-info/WHEEL
k2-1.24.1.dist-info/top_level.txt
k2-1.24.1.dist-info/RECORD
