Metadata-Version: 2.1
Name: k2
Version: 1.24.1
Summary: FSA/FST algorithms, intended to (eventually) be interoperable with PyTorch and similar
Home-page: https://github.com/k2-fsa/k2
Author: Daniel Povey
Author-email: dpovey@gmail.com
Keywords: k2,FSA,FST
Classifier: Development Status :: 3 - Alpha
Classifier: Programming Language :: Python :: 3
Classifier: Programming Language :: C++
Classifier: Programming Language :: Python :: Implementation :: CPython
Classifier: Topic :: Scientific/Engineering :: Artificial Intelligence
Requires-Python: >=3.6
License-File: LICENSE
Requires-Dist: torch (==1.13.1)
Requires-Dist: graphviz
Requires-Dist: typing-extensions ; python_version < "3.8"
Provides-Extra: dev
Requires-Dist: clang-format (==9.0.0) ; extra == 'dev'
Requires-Dist: flake8 (==3.8.3) ; extra == 'dev'
Requires-Dist: yapf (==0.27.0) ; extra == 'dev'
